checkopenbgpd/__init__.py
checkopenbgpd/checkopenbgpd.py
checkopenbgpd/tests/test_checkopenbgpd.py
checkopenbgpd-0.10.dist-info/DESCRIPTION.rst
checkopenbgpd-0.10.dist-info/METADATA
checkopenbgpd-0.10.dist-info/RECORD
checkopenbgpd-0.10.dist-info/WHEEL
checkopenbgpd-0.10.dist-info/entry_points.txt
checkopenbgpd-0.10.dist-info/metadata.json
checkopenbgpd-0.10.dist-info/top_level.txt
