Metadata-Version: 2.0
Name: checkopenbgpd
Version: 0.10
Summary: Check OpenBGPD sessions Nagios|Icinga|shinken|etc plugin
Home-page: https://github.com/jpcw/checkopenbgpd/
Author: Jean-Philippe Camguilhem
Author-email: pypi@camguilhem.net
License: BSD
Keywords: Nagios Icinga plugin check openbgpd openbsd monitoring
Platform: any
Classifier: Programming Language :: Python
Classifier: License :: OSI Approved :: BSD License
Classifier: Development Status :: 5 - Production/Stable
Classifier: Environment :: Plugins
Classifier: Intended Audience :: Developers
Classifier: Intended Audience :: System Administrators
Classifier: Operating System :: POSIX :: BSD :: OpenBSD
Classifier: Programming Language :: Python :: 2.7
Classifier: Programming Language :: Python :: 3.3
Classifier: Programming Language :: Python :: 3.4
Classifier: Programming Language :: Python :: 3.5
Classifier: Programming Language :: Python :: 3.6
Classifier: Programming Language :: Python :: Implementation :: CPython
Classifier: Programming Language :: Python :: Implementation :: PyPy
Classifier: Topic :: Software Development :: Libraries :: Python Modules
Classifier: Topic :: System :: Monitoring
Requires-Dist: nagiosplugin
Provides-Extra: test
Requires-Dist: mock; extra == 'test'
Requires-Dist: setuptools; extra == 'test'
